[
  { "sessionNumber": 219, "number": "219-閣法-1", "title": "ストーカー行為等の規制等に関する法律の一部を改正する法律案", "summary": "改正ストーカー規制法。GPS機器を用いた位置情報の取得規制強化、SNS等を通じたつきまとい行為への対応強化。", "proposer": "内閣", "category": "司法", "status": "ENACTED", "submittedAt": "2025-11-04", "passedAt": "2025-12-10" },
  { "sessionNumber": 219, "number": "219-閣法-2", "title": "配偶者からの暴力の防止及び被害者の保護等に関する法律の一部を改正する法律案", "summary": "改正DV防止法。接近禁止命令の対象拡大、精神的DV（モラハラ）に対する保護命令の適用等。", "proposer": "内閣", "category": "司法", "status": "ENACTED", "submittedAt": "2025-11-04", "passedAt": "2025-12-10" },
  { "sessionNumber": 219, "number": "219-衆法-1", "title": "租税特別措置法等の一部を改正する法律案", "summary": "ガソリン税暫定税率の廃止。旧暫定税率を廃止し、ガソリン価格の引下げを実現。", "proposer": "立憲民主党・日本維新の会・国民民主党・日本共産党・参政党・日本保守党・社会民主党", "category": "経済", "status": "ENACTED", "submittedAt": "2025-08-01", "passedAt": "2025-11-28" },
  { "sessionNumber": 217, "number": "217-閣法-1", "title": "所得税法等の一部を改正する法律案", "summary": "令和7年度税制改正。「103万円の壁」の見直し、防衛特別法人税の創設、賃上げ税制の延長等。", "proposer": "内閣", "category": "経済", "status": "ENACTED", "submittedAt": "2025-02-04", "passedAt": "2025-03-31" },
  { "sessionNumber": 217, "number": "217-閣法-4", "title": "重要電子計算機に対する不正な行為による被害の防止に関する法律案", "summary": "サイバー対処能力強化法（能動的サイバー防御法）。政府の能動的サイバー防御を可能とする制度を創設。", "proposer": "内閣", "category": "安全保障", "status": "ENACTED", "submittedAt": "2025-02-07", "passedAt": "2025-05-16" },
  { "sessionNumber": 217, "number": "217-閣法-21", "title": "医療DX推進法案", "summary": "電子カルテの標準化義務化、医療情報基盤の整備等。マイナ保険証の本格運用に伴うデジタル化推進。", "proposer": "内閣", "category": "社会保障", "status": "ENACTED", "submittedAt": "2025-02-28", "passedAt": "2025-05-23" },
  { "sessionNumber": 217, "number": "217-閣法-22", "title": "介護保険法等の一部を改正する法律案", "summary": "介護制度改革。介護職員の処遇改善、ケアマネジメントの質の向上、地域包括ケアシステムの深化・推進等。", "proposer": "内閣", "category": "社会保障", "status": "ENACTED", "submittedAt": "2025-02-28", "passedAt": "2025-05-30" },
  { "sessionNumber": 217, "number": "217-閣法-29", "title": "人工知能関連技術の研究開発及び活用の推進に関する法律案", "summary": "AI基本法。AI利活用の基本原則、リスク管理体制の整備、AI安全研究所の法的位置づけ等。", "proposer": "内閣", "category": "科学技術", "status": "ENACTED", "submittedAt": "2025-02-28", "passedAt": "2025-05-28" },
  { "sessionNumber": 217, "number": "217-閣法-59", "title": "年金制度の機能強化のための国民年金法等の一部を改正する等の法律案", "summary": "年金制度改革法。「106万円の壁」の撤廃、在職老齢年金制度の見直し、基礎年金の給付水準底上げ等。", "proposer": "内閣", "category": "社会保障", "status": "ENACTED", "submittedAt": "2025-05-16", "passedAt": "2025-06-13" },
  { "sessionNumber": 217, "number": "217-衆法-11", "title": "手話言語法案", "summary": "手話を言語として法的に位置づけ、手話の普及・研究・利用促進に関する施策を規定。", "proposer": "超党派", "category": "社会保障", "status": "ENACTED", "submittedAt": "2025-04-22", "passedAt": "2025-06-18" },
  { "sessionNumber": 216, "number": "216-衆法-2", "title": "政治資金規正法の一部を改正する法律案（政策活動費廃止）", "summary": "政策活動費の廃止。政党から議員個人に支給される政策活動費を渡切りの方法により支出することを禁止。", "proposer": "立憲民主党・日本維新の会・国民民主党・日本共産党・参政党・日本保守党・社会民主党", "category": "行政", "status": "ENACTED", "submittedAt": "2024-12-04", "passedAt": "2024-12-24" },
  { "sessionNumber": 216, "number": "216-衆法-11", "title": "政治資金監視委員会設置法案", "summary": "国会に独立性の高い「政治資金監視委員会」を設置し、政治資金の監視・検査機能を強化。", "proposer": "国民民主党・公明党", "category": "行政", "status": "ENACTED", "submittedAt": "2024-12-09", "passedAt": "2024-12-24" },
  { "sessionNumber": 213, "number": "213-閣法-1", "title": "所得税法等の一部を改正する法律案", "summary": "定額減税の実施、扶養控除の見直し等を含む税制改正法案。", "proposer": "内閣", "category": "経済", "status": "ENACTED", "submittedAt": "2024-02-02", "passedAt": "2024-03-28" },
  { "sessionNumber": 213, "number": "213-閣法-22", "title": "子ども・子育て支援法等の一部を改正する法律案", "summary": "児童手当の拡充（所得制限撤廃・高校生まで延長）、こども誰でも通園制度の創設等。", "proposer": "内閣", "category": "社会保障", "status": "ENACTED", "submittedAt": "2024-02-16", "passedAt": "2024-06-05" },
  { "sessionNumber": 213, "number": "213-閣法-24", "title": "重要経済安保情報の保護及び活用に関する法律案", "summary": "セキュリティ・クリアランス法。経済安全保障上重要な情報にアクセスする者の適性評価制度を創設。", "proposer": "内閣", "category": "安全保障", "status": "ENACTED", "submittedAt": "2024-02-27", "passedAt": "2024-05-10" },
  { "sessionNumber": 213, "number": "213-閣法-47", "title": "民法等の一部を改正する法律案", "summary": "共同親権導入。離婚後も父母が共同で親権を行使することを選択できる制度を導入。77年ぶりの親権制度の大改正。", "proposer": "内閣", "category": "司法", "status": "ENACTED", "submittedAt": "2024-03-08", "passedAt": "2024-05-17" },
  { "sessionNumber": 213, "number": "213-閣法-62", "title": "スマホソフトウェア競争促進法案", "summary": "Apple・Googleのアプリストア独占に対応し、サイドローディングの義務化等。日本版デジタル市場法。", "proposer": "内閣", "category": "経済", "status": "ENACTED", "submittedAt": "2024-04-26", "passedAt": "2024-06-12" },
  { "sessionNumber": 213, "number": "213-衆法-16", "title": "政治資金規正法の一部を改正する法律案", "summary": "改正政治資金規正法。政治資金パーティー収入の公開基準引下げ、政策活動費の使途公開。", "proposer": "自由民主党", "category": "行政", "status": "ENACTED", "submittedAt": "2024-05-31", "passedAt": "2024-06-19" },
  { "sessionNumber": 213, "number": "213-衆法-8", "title": "消費税率の引下げ等に関する法律案", "summary": "消費税率の時限的な5%への引下げ。物価高騰対策としての消費税減税を提案。", "proposer": "日本維新の会", "category": "経済", "status": "REJECTED", "submittedAt": "2024-03-01" },
  { "sessionNumber": 213, "number": "213-参法-3", "title": "選択的夫婦別姓制度を導入する民法の一部を改正する法律案", "summary": "婚姻時に夫婦が各自の氏を称することを選択できる制度の導入。", "proposer": "立憲民主党", "category": "司法", "status": "COMMITTEE", "submittedAt": "2024-02-14" },
  { "sessionNumber": 212, "number": "212-閣法-1", "title": "一般職の職員の給与に関する法律等の一部を改正する法律案", "summary": "人事院勧告に基づく国家公務員の給与改定。月例給・ボーナスの引上げ。", "proposer": "内閣", "category": "行政", "status": "ENACTED", "submittedAt": "2023-10-31", "passedAt": "2023-11-15" },
  { "sessionNumber": 211, "number": "211-閣法-1", "title": "所得税法等の一部を改正する法律案", "summary": "令和5年度税制改正。NISA拡充・恒久化、インボイス制度の激変緩和措置等。", "proposer": "内閣", "category": "経済", "status": "ENACTED", "submittedAt": "2023-02-03", "passedAt": "2023-03-28" },
  { "sessionNumber": 211, "number": "211-閣法-12", "title": "マイナンバー法等の一部を改正する法律案", "summary": "マイナンバーカードと健康保険証の一体化、マイナンバーの利用範囲拡大等。", "proposer": "内閣", "category": "行政", "status": "ENACTED", "submittedAt": "2023-03-07", "passedAt": "2023-06-02" },
  { "sessionNumber": 211, "number": "211-閣法-16", "title": "入管法改正案", "summary": "難民認定申請中の送還停止効の例外規定、監理措置制度の創設等。入管収容の見直し。", "proposer": "内閣", "category": "社会保障", "status": "ENACTED", "submittedAt": "2023-03-07", "passedAt": "2023-06-09" },
  { "sessionNumber": 211, "number": "211-衆法-25", "title": "LGBT理解増進法案", "summary": "性的指向及びジェンダーアイデンティティの多様性に関する国民の理解増進。", "proposer": "自由民主党", "category": "社会保障", "status": "ENACTED", "submittedAt": "2023-06-09", "passedAt": "2023-06-16" },
  { "sessionNumber": 210, "number": "210-閣法-1", "title": "一般職の職員の給与に関する法律等の一部を改正する法律案", "summary": "人事院勧告に基づく国家公務員給与改定。月例給・ボーナスの引上げ。", "proposer": "内閣", "category": "行政", "status": "ENACTED", "submittedAt": "2022-10-07", "passedAt": "2022-11-11" },
  { "sessionNumber": 210, "number": "210-閣法-5", "title": "感染症の予防及び感染症の患者に対する医療に関する法律等の一部を改正する法律案", "summary": "次の感染症危機に備えた医療提供体制の強化。病床確保の義務化等。", "proposer": "内閣", "category": "社会保障", "status": "ENACTED", "submittedAt": "2022-10-07", "passedAt": "2022-12-02" },
  { "sessionNumber": 210, "number": "210-閣法-22", "title": "法人等による寄附の不当な勧誘の防止等に関する法律案", "summary": "旧統一教会被害者救済法。不当な勧誘による困惑行為の禁止、寄附の意思表示の取消権等。", "proposer": "内閣", "category": "司法", "status": "ENACTED", "submittedAt": "2022-12-01", "passedAt": "2022-12-10" }
]
